hypermodern_cookiecutter_example/__init__.py
hypermodern_cookiecutter_example/__main__.py
hypermodern_cookiecutter_example/py.typed
hypermodern_cookiecutter_example-0.0.0.dist-info/entry_points.txt
hypermodern_cookiecutter_example-0.0.0.dist-info/LICENSE
hypermodern_cookiecutter_example-0.0.0.dist-info/WHEEL
hypermodern_cookiecutter_example-0.0.0.dist-info/METADATA
hypermodern_cookiecutter_example-0.0.0.dist-info/RECORD
