Metadata-Version: 2.1
Name: hypermodern-cookiecutter-example
Version: 0.0.0
Summary: Hypermodern Cookiecutter Example
Home-page: https://github.com/paulrousset/hypermodern-cookiecutter-example
License: MIT
Author: Paul Rousset
Author-email: paulrousset@hotmail.fr
Requires-Python: >=3.7,<4.0
Classifier: Development Status :: 1 - Planning
Classifier: License :: OSI Approved :: MIT License
Classifier: Programming Language :: Python :: 3
Classifier: Programming Language :: Python :: 3.10
Classifier: Programming Language :: Python :: 3.7
Classifier: Programming Language :: Python :: 3.8
Classifier: Programming Language :: Python :: 3.9
Requires-Dist: click (>=8.0.1)
Project-URL: Changelog, https://github.com/paulrousset/hypermodern-cookiecutter-example/releases
Project-URL: Documentation, https://hypermodern-cookiecutter-example.readthedocs.io
Project-URL: Repository, https://github.com/paulrousset/hypermodern-cookiecutter-example
